playful/__init__.py
playful/api/__init__.py
playful/api/api.py
playful/component/__init__.py
playful/component/component.py
playful/component/inhibition.py
playful/component/memory_getter.py
playful/component/property.py
playful/component/resources_manager.py
playful/component/spineable.py
playful/display/__init__.py
playful/display/display.py
playful/engine/__init__.py
playful/engine/run.py
playful/interpreter/__init__.py
playful/interpreter/args.py
playful/interpreter/directory.py
playful/interpreter/evaluation.py
playful/interpreter/instantiable.py
playful/interpreter/interpreter.py
playful/interpreter/lib.py
playful/interpreter/parsing.py
playful/interpreter/preprocessed_calculator.py
playful/interpreter/preprocessed_word.py
playful/interpreter/score_calculator.py
playful/interpreter/state_transition.py
playful/interpreter/subevaluation.py
playful/interpreter/vocabulary.py
playful/interpreter/word.py
playful/interpreter/workspace.py
playful/memory/__init__.py
playful/memory/memory.py
playful/orchestration/__init__.py
playful/orchestration/behavior_container.py
playful/orchestration/evaluable.py
playful/orchestration/resource_management.py
playful/orchestration/scoreable.py
playful/orchestration/state_container.py
playful/orchestration/statement.py
playful/orchestration/transitable.py
playful/resources/__init__.py
playful/resources/resources.py
playful/terminal/__init__.py
playful/terminal/terminal.py
playful-1.12.data/scripts/playful
playful-1.12.dist-info/METADATA
playful-1.12.dist-info/WHEEL
playful-1.12.dist-info/top_level.txt
playful-1.12.dist-info/zip-safe
playful-1.12.dist-info/RECORD
