Metadata-Version: 2.1
Name: playful
Version: 1.12
Summary: an interpreter for reactive programming
Home-page: UNKNOWN
Author: UNKNOWN
Author-email: UNKNOWN
License: UNKNOWN
Platform: UNKNOWN
Requires-Dist: funcsigs
